txagent/__init__.py
txagent/toolrag.py
txagent/txagent.py
txagent/utils.py
txagent-0.1.3.dist-info/licenses/LICENSE
txagent-0.1.3.dist-info/METADATA
txagent-0.1.3.dist-info/WHEEL
txagent-0.1.3.dist-info/top_level.txt
txagent-0.1.3.dist-info/RECORD
