Metadata-Version: 2.4
Name: txagent
Version: 0.1.3
Summary: TxAgent: An AI Agent for Therapeutic Reasoning Across a Universe of Tools
Home-page: https://github.com/mims-harvard/TxAgent
Author: Shanghua Gao
Author-email: shanghuagao@gmail.com
Requires-Python: >=3.6
License-File: LICENSE
Requires-Dist: gradio
Requires-Dist: vllm<=0.8.4
Requires-Dist: sentence_transformers
Dynamic: license-file
